tm1cm/__init__.py
tm1cm/__main__.py
tm1cm/application.py
tm1cm/common.py
tm1cm/interactive.py
tm1cm/migration.py
tm1cm/operation.py
tm1cm/scaffold.py
tm1cm/ti_format.py
tm1cm/include/.gitignore
tm1cm/include/connect.yaml
tm1cm/include/credentials.yaml
tm1cm/include/tm1cm.yaml
tm1cm-0.9.5.dist-info/LICENSE
tm1cm-0.9.5.dist-info/METADATA
tm1cm-0.9.5.dist-info/WHEEL
tm1cm-0.9.5.dist-info/entry_points.txt
tm1cm-0.9.5.dist-info/top_level.txt
tm1cm-0.9.5.dist-info/RECORD
