Metadata-Version: 2.1
Name: tm1cm
Version: 0.9.5
Summary: A model migration library for TM1 Planning Analytics
Home-page: https://github.com/ajmyers/tm1cm
Author: Andrew Myers
Author-email: me@ajmyers.net
License: UNKNOWN
Project-URL: Bug Reports, https://github.com/ajmyers/tm1cm/issues
Project-URL: Source, https://github.com/ajmyers/tm1cm
Keywords: tm1,planning analytics,ibm,pa,olap,cube
Platform: UNKNOWN
Classifier: Development Status :: 5 - Production/Stable
Classifier: Intended Audience :: Developers
Classifier: Topic :: Software Development :: Build Tools
Classifier: License :: OSI Approved :: GNU General Public License v3 or later (GPLv3+)
Classifier: Programming Language :: Python :: 3
Classifier: Programming Language :: Python :: 3.7
Classifier: Programming Language :: Python :: 3.8
Classifier: Programming Language :: Python :: 3.9
Classifier: Programming Language :: Python :: 3.10
Classifier: Programming Language :: Python :: 3 :: Only
Requires-Python: >=3.7, <4
License-File: LICENSE
Requires-Dist: TM1py (<=1.11.3,>=1.2.1)
Requires-Dist: gitdb2 (==2.0.5)
Requires-Dist: GitPython (==2.1.11)
Requires-Dist: termcolor (==1.1.0)
Requires-Dist: ntplib (==0.3.4)
Requires-Dist: pyyaml (==6.0)
